medium_article_parser/__init__.py
medium_article_parser/document_parser.py
medium_article_parser/medium_discovery.py
medium_article_parser-0.1.0.dist-info/LICENSE
medium_article_parser-0.1.0.dist-info/METADATA
medium_article_parser-0.1.0.dist-info/WHEEL
medium_article_parser-0.1.0.dist-info/top_level.txt
medium_article_parser-0.1.0.dist-info/RECORD
