Metadata-Version: 2.2
Name: medium-article-parser
Version: 0.1.0
Summary: A Python package to discover and parse Medium articles
Author-email: Om Maniya <maniyaom592@gmail.com>
License: MIT License
Project-URL: Homepage, https://github.com/664223/medium-article-parser
Keywords: medium,parser,articles
Classifier: License :: OSI Approved :: MIT License
Classifier: Programming Language :: Python
Classifier: Programming Language :: Python :: 3
Requires-Python: >=3.7
License-File: LICENSE
Requires-Dist: requests>=2.25.0
Requires-Dist: beautifulsoup4>=4.9.0
